ash_dal/__init__.py
ash_dal/constants.py
ash_dal/dao/__init__.py
ash_dal/dao/async_dao.py
ash_dal/dao/mixin.py
ash_dal/dao/sync_dao.py
ash_dal/database/__init__.py
ash_dal/database/async_database.py
ash_dal/database/sync_database.py
ash_dal/database/sync_session.py
ash_dal/exceptions/__init__.py
ash_dal/exceptions/database.py
ash_dal/typing.py
ash_dal/utils/__init__.py
ash_dal/utils/paginator/__init__.py
ash_dal/utils/paginator/async_paginator.py
ash_dal/utils/paginator/base.py
ash_dal/utils/paginator/factory.py
ash_dal/utils/paginator/interface.py
ash_dal/utils/paginator/paginator_page.py
ash_dal/utils/paginator/sync_paginator.py
ash_dal/utils/ssl.py
ash_dal-0.4.0.dist-info/METADATA
ash_dal-0.4.0.dist-info/WHEEL
ash_dal-0.4.0.dist-info/RECORD
