Metadata-Version: 2.3
Name: ash-dal
Version: 0.4.0
Summary: The library provides a standardized way to connect to DB, and Base DAO class implementation
Author: Dmitry Marchuk
Author-email: dmarchuk@remedypointsolutions.com
Requires-Python: >=3.11,<4.0
Classifier: Programming Language :: Python :: 3
Classifier: Programming Language :: Python :: 3.11
Classifier: Programming Language :: Python :: 3.12
Classifier: Programming Language :: Python :: 3.13
Requires-Dist: SQLAlchemy (>=2.0.44,<3.0.0)
Requires-Dist: aiomysql (>=0.3.0,<0.4.0)
Requires-Dist: pymysql (>=1.1.2,<2.0.0)
